[
  {
    "siteTitle": "Dina Portfolio",

    "hero": {
      "title": "Graphic Designer",
      "subtitle": "Branding, Motion Graphics & Visual Design",
      "backgroundImage": {
        "url": "/uploads/site/hero.webp",
        "alt": "Homepage hero background"
      }
    },

    "about": {
      "title": "About Me",
      "bio": "I'm a multidisciplinary graphic designer specializing in branding, esports and live event graphics.",
      "profileImage": {
        "url": "/uploads/site/profile.webp",
        "alt": "Portrait of Dina"
      },      
      "software": ["Adobe Illustrator", "Adobe Photoshop"],
      "languages": ["English", "Spanish", "Arabic"]
    },

    "contact": {
      "email": "dina@example.com",
      "phone": "+34 600 123 456",
      "location": "Seville, Spain"
    },

    "socialLinks": {
      "linkedin": "https://linkedin.com/in/dina"
    },

    "createdAt": "2026-07-12T18:00:00.000Z",
    "updatedAt": "2026-07-12T18:00:00.000Z"
  }
]